{
    "id": 219,
    "title": "द्वादश ज्योतिर्लिंग स्तोत्रम्",
    "titleEn": "Dwadasha Jyotirlinga Stotram",
    "slug": "dwadasha-jyotirlinga-stotram",
    "devanagariText": "॥ श्री द्वादश ज्योतिर्लिंग स्तोत्रम् ॥\n\nसौराष्ट्रे सोमनाथं च श्रीशैले मल्लिकार्जुनम्।\nउज्जयिन्यां महाकालमोंकारममलेश्वरम्॥ १॥\n\nपरल्यां वैद्यनाथं च डाकिन्यां भीमशंकरम्।\nसेतुबन्धे तु रामेशं नागेशं दारुकावने॥ २॥\n\nवाराणस्यां तु विश्वेशं त्र्यम्बकं गौतमीतटे।\nहिमालये तु केदारं घुश्मेशं च शिवालये॥ ३॥\n\nएतानि ज्योतिर्लिंगानि सायं प्रातः पठेन्नरः।\nसप्तजन्मकृतं पापं स्मरणेन विनश्यति॥ ४॥\n\n॥ इति श्री द्वादश ज्योतिर्लिंग स्तोत्रम् सम्पूर्णम् ॥",
    "transliteration": "",
    "hindiMeaning": "",
    "viniyog": null,
    "benefits": [
        "Sacred Dwadasha Jyotirlinga Stotram for devotion and spiritual growth",
        "Invokes blessings of Shiva in all forms",
        "Grants divine protection and auspiciousness",
        "Removes sins and bestows spiritual merit",
        "Ideal for Shiva festivals and daily worship"
    ],
    "deity": "shiva",
    "secondaryDeities": [
        "parvati"
    ],
    "days": [
        "monday"
    ],
    "festivals": [
        "maha-shivaratri"
    ],
    "purposes": [
        "devotion",
        "sin-removal",
        "pilgrimage",
        "peace"
    ],
    "readingTimeMinutes": 2,
    "seoDescription": "Read Dwadasha Jyotirlinga Stotram in Sanskrit with Hindi meaning. Sacred hymn for Shiva devotion.",
    "verseCount": 4,
    "source": "Shiva Purana",
    "createdAt": "2026-03-29T00:00:00Z",
    "updatedAt": "2026-03-29T00:00:00Z",
    "isPublished": true
}