{
  "id": "305",
  "title": "हनुमान अष्टोत्तर शतनामावली",
  "titleEn": "Hanuman Ashtottara Shatanamavali",
  "slug": "hanuman-ashtottara-shatanamavali",
  "devanagariText": "॥ श्री हनुमान अष्टोत्तर शतनामावली ॥\n\nॐ आञ्जनेयाय नमः\nॐ महावीराय नमः\nॐ हनूमते नमः\nॐ मारुतात्मजाय नमः\nॐ तत्त्वज्ञानप्रदाय नमः\nॐ सीतादेवीमुद्राप्रदायकाय नमः\nॐ अशोकवनिकाच्छेत्रे नमः\nॐ सर्वमायाविभञ्जनाय नमः\nॐ सर्वबन्धविमोक्त्रे नमः\nॐ रक्षोविध्वंसकारकाय नमः\nॐ परविद्यापरिहर्त्रे नमः\nॐ परशौर्यविनाशनाय नमः\nॐ परमन्त्रनिराकर्त्रे नमः\nॐ परयन्त्रप्रभेदकाय नमः\nॐ सर्वग्रहविनाशिने नमः\nॐ भीमसेनसहायकृते नमः\nॐ सर्वदुःखहराय नमः\nॐ सर्वलोकचारिणे नमः\nॐ मनोजवाय नमः\nॐ पारिजातद्रुमूलस्थाय नमः\nॐ सर्वमन्त्रस्वरूपवते नमः\nॐ सर्वतन्त्रस्वरूपिणे नमः\nॐ सर्वयन्त्रात्मकाय नमः\nॐ कपीश्वराय नमः\nॐ महाकायाय नमः\nॐ सर्वरोगहराय नमः\nॐ प्रभवे नमः\nॐ बलसिद्धिकराय नमः\nॐ सर्वविद्यासम्पत्प्रदायकाय नमः\nॐ कपिसेनानायकाय नमः\nॐ भविष्यच्चतुरानन्दाय नमः\nॐ कुमारब्रह्मचारिणे नमः\nॐ रत्नकुण्डलदीप्तिमते नमः\nॐ सञ्चलद्वालसन्नद्धलम्बमानशिखोज्ज्वलाय नमः\nॐ गन्धर्ववाचनतत्त्वज्ञाय नमः\nॐ महाबलपराक्रमाय नमः\nॐ कारागृहविमोक्त्रे नमः\nॐ शृङ्खलाबन्धमोचकाय नमः\nॐ सागरोत्तारकाय नमः\nॐ प्राज्ञाय नमः\nॐ रामदूताय नमः\nॐ प्रतापवते नमः\nॐ वानराय नमः\nॐ केसरीसुताय नमः\nॐ सीताशोकनिवारणाय नमः\nॐ अञ्जनागर्भसम्भूताय नमः\nॐ बालार्कसदृशाननाय नमः\nॐ विभीषणप्रियकराय नमः\nॐ दशग्रीवकुलान्तकाय नमः\nॐ लक्ष्मणप्राणदात्रे नमः\nॐ वज्रकायाय नमः\nॐ महाद्युतये नमः\nॐ चिरञ्जीविने नमः\nॐ रामभक्ताय नमः\nॐ दैत्यकार्यविघातकाय नमः\nॐ अक्षहन्त्रे नमः\nॐ काञ्चनाभाय नमः\nॐ पञ्चवक्त्राय नमः\nॐ महातपसे नमः\nॐ लङ्किणीभञ्जनाय नमः\nॐ श्रीमते नमः\nॐ सिंहिकाप्राणभञ्जनाय नमः\nॐ गन्धमादनशैलस्थाय नमः\nॐ लङ्कापुरविदाहकाय नमः\nॐ सुग्रीवसचिवाय नमः\nॐ धीराय नमः\nॐ शूराय नमः\nॐ दैत्यकुलान्तकाय नमः\nॐ सुरार्चिताय नमः\nॐ महातेजसे नमः\nॐ रामचूडामणिप्रदाय नमः\nॐ कामरूपिणे नमः\nॐ पिङ्गलाक्षाय नमः\nॐ वार्धिमैनाकपूजिताय नमः\nॐ कबलीकृतमार्ताण्डमण्डलाय नमः\nॐ विजितेन्द्रियाय नमः\nॐ रामसुग्रीवसन्धात्रे नमः\nॐ महारावणमर्दनाय नमः\nॐ स्फटिकाभाय नमः\nॐ वागधीशाय नमः\nॐ नवव्याकृतिपण्डिताय नमः\nॐ चतुर्बाहवे नमः\nॐ दीनबन्धवे नमः\nॐ महात्मने नमः\nॐ भक्तवत्सलाय नमः\nॐ सञ्जीवननगार्याय नमः\nॐ शुचये नमः\nॐ वाग्मिने नमः\nॐ दृढव्रताय नमः\nॐ कालनेमिप्रमथनाय नमः\nॐ हरिमर्कटमर्कटाय नमः\nॐ दान्ताय नमः\nॐ शान्ताय नमः\nॐ प्रसन्नात्मने नमः\nॐ शतकण्ठमदापहृते नमः\nॐ योगिने नमः\nॐ रामकथालोलाय नमः\nॐ सीतान्वेषणपण्डिताय नमः\nॐ वज्रदंष्ट्राय नमः\nॐ वज्रनखाय नमः\nॐ रुद्रवीर्यसमुद्भवाय नमः\nॐ इन्द्रजित्प्रहितामोघब्रह्मास्त्रविनिवारकाय नमः\nॐ पार्थध्वजाग्रसंवासिने नमः\nॐ शरपञ्जरभेदकाय नमः\nॐ दशबाहवे नमः\nॐ लोकपूज्याय नमः\nॐ जाम्बवत्प्रीतिवर्धनाय नमः\nॐ सीताराममुखापातरसपात्राय नमः\nॐ भक्तोद्धारकाय नमः\nॐ श्रीपवननन्दनाय नमः\n\n॥ इति श्री हनुमान अष्टोत्तर शतनामावली सम्पूर्ण ॥",
  "transliteration": "|| Shri Hanuman Ashtottara Shatanamavali ||\n\nOm Aanjaneyaya Namah\nOm Mahaviraya Namah\nOm Hanumate Namah\nOm Marutatmajaya Namah\nOm Tattvajnanapradaya Namah\nOm Sitadevimudrapradayakaya Namah\nOm Ashokavanikacchhetre Namah\nOm Sarvamayavibhanjanaya Namah\nOm Sarvabandhavimoktre Namah\nOm Rakshovidhvansakarakaya Namah\nOm Paravidyaparihartre Namah\nOm Parashauryavinashanaya Namah\nOm Paramantranirakartre Namah\nOm Parayantraprabhedakaya Namah\nOm Sarvagrahavinshine Namah\nOm Bhimasenasahayakrite Namah\nOm Sarvaduhkhaharaya Namah\nOm Sarvalokacharine Namah\nOm Manojavaya Namah\nOm Parijatadrumulasthaya Namah\nOm Sarvamantraswarupavate Namah\nOm Sarvatantraswarupine Namah\nOm Sarvayantratmakaya Namah\nOm Kapishwaraya Namah\nOm Mahakayaya Namah\nOm Sarvarogaharaya Namah\nOm Prabhave Namah\nOm Balasiddhikaraya Namah\nOm Sarvavidyasampatpradayakaya Namah\nOm Kapisenanyakaya Namah\nOm Bhavishyachchaturanandaya Namah\nOm Kumarabrahmacharine Namah\nOm Ratnakundaladiptimate Namah\nOm Sanchaladvalsannaddhlambamanashikhojjvalaya Namah\nOm Gandharvavachanatattvajnaya Namah\nOm Mahabalaprakramaya Namah\nOm Karagrihavimoktré Namah\nOm Shrinkhalabandhamochakaya Namah\nOm Sagarottarakaya Namah\nOm Prajnaya Namah\nOm Ramadutaya Namah\nOm Pratapavate Namah\nOm Vanaraya Namah\nOm Kesarisutaya Namah\nOm Sitashokanivaranaya Namah\nOm Anjanagarbhasambhutaya Namah\nOm Balarkasadrshanannaya Namah\nOm Vibhishanapriyakaraya Namah\nOm Dashagrivakulantakaya Namah\nOm Lakshmanapranadatre Namah\nOm Vajrakayaya Namah\nOm Mahadyutaye Namah\nOm Chiranjeevine Namah\nOm Ramabhaktaya Namah\nOm Daityakaryavighatakaya Namah\nOm Akshahantre Namah\nOm Kanchanabhaya Namah\nOm Panchavaktraya Namah\nOm Mahatapase Namah\nOm Lankinibhanjanaya Namah\nOm Shrimate Namah\nOm Simhikapranabhanjanaya Namah\nOm Gandhamadanashailasthaya Namah\nOm Lankapuravidahakaya Namah\nOm Sugrivasachivaya Namah\nOm Dhiraya Namah\nOm Shuraya Namah\nOm Daityakulantakaya Namah\nOm Surarchitaya Namah\nOm Mahatejase Namah\nOm Ramachudamanipradaya Namah\nOm Kamarupine Namah\nOm Pingalakshaya Namah\nOm Vardhimainakpujitaya Namah\nOm Kabalikritamartandamandalaya Namah\nOm Vijitendriyaya Namah\nOm Ramasugriivasandhatre Namah\nOm Maharavanamarddanaya Namah\nOm Sphatikabhaya Namah\nOm Vagadhishaya Namah\nOm Navavyakritipanditaya Namah\nOm Chaturbahave Namah\nOm Dinabandhave Namah\nOm Mahatmane Namah\nOm Bhaktavatsalaya Namah\nOm Sanjivananagaryaya Namah\nOm Shuchaye Namah\nOm Vagmine Namah\nOm Dridhavrataya Namah\nOm Kalanemipramthanaya Namah\nOm Harimarkatamarkataya Namah\nOm Dantaya Namah\nOm Shantaya Namah\nOm Prasannatmane Namah\nOm Shatakanthamadapahrite Namah\nOm Yogine Namah\nOm Ramakathalolaaya Namah\nOm Sitanveshanapanditaya Namah\nOm Vajradamshtraya Namah\nOm Vajranakhaya Namah\nOm Rudraviryasamudbhavaya Namah\nOm Indrajitprahitamoghbrahmastravinivaarakaya Namah\nOm Parthadhvajagrasamvasine Namah\nOm Sharapanjarabhedakaya Namah\nOm Dashabahave Namah\nOm Lokapujyaya Namah\nOm Jambavatpritivardhanaya Namah\nOm Sitaramamukhapatrarasapatraya Namah\nOm Bhaktoddharakaya Namah\nOm Shri Pavananandanaya Namah\n\n|| Iti Shri Hanuman Ashtottara Shatanamavali Sampurna ||",
  "hindiMeaning": "हनुमान अष्टोत्तर शतनामावली भगवान हनुमान के 108 पवित्र नामों का संग्रह है। इन नामों में हनुमान जी के विभिन्न रूपों, शक्तियों और गुणों का वर्णन है - आञ्जनेय (अंजनी पुत्र), महावीर (महान वीर), मारुतात्मज (वायुपुत्र), रामदूत (राम के दूत), कपीश्वर (वानरों के ईश्वर), पञ्चवक्त्र (पंचमुखी), चिरञ्जीवी (अमर), पवननन्दन (पवन के पुत्र) आदि।",
  "viniyog": null,
  "benefits": [
    "Reciting 108 names of Hanuman bestows immense strength and courage",
    "Removes all fears, evil spirits, and planetary afflictions",
    "Cures diseases and removes all forms of suffering",
    "Used during Hanuman puja, archana, and abhishek",
    "Particularly powerful on Tuesdays, Saturdays, and Hanuman Jayanti"
  ],
  "deity": "hanuman",
  "secondaryDeities": ["rama"],
  "days": ["tuesday", "saturday"],
  "festivals": ["hanuman-jayanti"],
  "purposes": ["protection", "strength", "health", "archana-puja"],
  "readingTimeMinutes": 15,
  "seoDescription": "Hanuman Ashtottara Shatanamavali - 108 names of Lord Hanuman in Sanskrit with transliteration. For Hanuman puja and Tuesday-Saturday worship.",
  "verseCount": 108,
  "source": "Parasara Smriti / Hanuman tradition",
  "createdAt": "2026-03-28T00:00:00Z",
  "updatedAt": "2026-03-28T00:00:00Z",
  "isPublished": true
}