{
    "id": "638",
    "title": "श्रीहरि स्तुति",
    "titleEn": "Shri Hari Stuti",
    "slug": "shri-hari-stuti",
    "devanagariText": "॥ श्रीहरि स्तुति ॥\n\nश्रियः कान्ताय कल्याणनिधये निधयेऽर्थिनाम्।\nश्रीवेङ्कटनिवासाय श्रीनिवासाय मंगलम्॥ १॥\n\nनारायण नारायण जय गोविन्द हरे।\nनारायण नारायण जय गोपाल हरे॥ २॥\n\nसर्वधर्मान्परित्यज्य मामेकं शरणं व्रज।\nअहं त्वां सर्वपापेभ्यो मोक्षयिष्यामि मा शुचः॥ ३॥\n\nहरिर्दाता हरिर्भोक्ता हरिरन्नं प्रजापतिः।\nहरिः सर्वशरीरस्थो भुंक्ते भोजयते हरिः॥ ४॥\n\nसर्वे भवन्तु सुखिनः सर्वे सन्तु निरामयाः।\nसर्वे भद्राणि पश्यन्तु मा कश्चिद्दुःखभाग्भवेत्॥ ५॥\n\nवासुदेवसुतं देवं कंसचाणूरमर्दनम्।\nदेवकीपरमानन्दं कृष्णं वन्दे जगद्गुरुम्॥ ६॥\n\nकृष्णाय वासुदेवाय हरये परमात्मने।\nप्रणतक्लेशनाशाय गोविन्दाय नमो नमः॥ ७॥\n\nॐ नमो भगवते वासुदेवाय नमः।\nॐ नमो नारायणाय नमः।\nहरे कृष्ण हरे कृष्ण कृष्ण कृष्ण हरे हरे।\nहरे राम हरे राम राम राम हरे हरे॥ ८॥\n\n॥ इति श्रीहरि स्तुति सम्पूर्णम् ॥",
    "transliteration": "|| Shri Hari Stuti ||\n\nShriyah Kantaya Kalyana Nidhaye Nidhaye'rthinam |\nShri Venkata Nivasaya Shri Nivasaya Mangalam || 1 ||\n\nNarayana Narayana Jaya Govinda Hare |\nNarayana Narayana Jaya Gopala Hare || 2 ||\n\nSarva Dharman Parityajya Mam Ekam Sharanam Vraja |\nAham Tvam Sarva Papebhyo Mokshayishyami Ma Shuchah || 3 ||\n\nHarir Data Harir Bhokta Harir Annam Prajapatih |\nHarih Sarva Sharira Stho Bhunkte Bhojayate Harih || 4 ||\n\nSarve Bhavantu Sukhinah Sarve Santu Niramayah |\nSarve Bhadrani Pashyantu Ma Kashchid Duhkhabhag Bhavet || 5 ||\n\nVasudevasutam Devam Kamsa Chanura Mardanam |\nDevaki Paramanandaam Krishnam Vande Jagadgurum || 6 ||\n\nKrishnaya Vasudevaya Haraye Paramatmane |\nPranata Klesha Nashaya Govindaya Namo Namah || 7 ||\n\nOm Namo Bhagavate Vasudevaya Namah |\nOm Namo Narayanaya Namah |\nHare Krishna Hare Krishna Krishna Krishna Hare Hare |\nHare Rama Hare Rama Rama Rama Hare Hare || 8 ||\n\n|| Iti Shri Hari Stuti Sampurnam ||",
    "hindiMeaning": "श्री (लक्ष्मी) के कान्त, कल्याणनिधि, याचकों के निधि, श्रीवेंकट में निवास करने वाले श्रीनिवास को मंगल हो।\n\nनारायण नारायण! जय गोविन्द हरे! जय गोपाल हरे!\n\n(गीता १८.६६) सब धर्मों को त्यागकर मेरी एक शरण में आओ। मैं तुम्हें सब पापों से मुक्त करूंगा, शोक मत करो।\n\nहरि ही दाता हैं, हरि ही भोक्ता हैं, हरि ही अन्न हैं, हरि ही प्रजापति हैं। हरि सबके शरीर में स्थित हैं — हरि ही खाते हैं और खिलाते हैं।\n\nसब सुखी हों, सब निरोग हों, सब कल्याण देखें, कोई दुःख का भागी न हो।\n\nवासुदेव के पुत्र, कंस-चाणूर को मारने वाले, देवकी के परमानन्द, जगद्गुरु कृष्ण को वन्दन।\n\nकृष्ण, वासुदेव, हरि, परमात्मा, शरणागतों के क्लेश नाश करने वाले गोविन्द को बारम्बार नमस्कार।\n\nहरे कृष्ण हरे कृष्ण कृष्ण कृष्ण हरे हरे। हरे राम हरे राम राम राम हरे हरे।",
    "viniyog": null,
    "benefits": [
        "Universal Hari stuti combining the most beloved Vishnu/Krishna verses",
        "Contains Bhagavad Gita's Charama Shloka (18.66) — supreme surrender verse",
        "Includes the universal prayer Sarve Bhavantu Sukhinah",
        "Ends with Hare Krishna Maha Mantra for nama sankeertana",
        "Perfect for daily devotional recitation by all Vaishnavas"
    ],
    "deity": "vishnu",
    "secondaryDeities": [
        "krishna",
        "lakshmi"
    ],
    "days": [
        "daily"
    ],
    "festivals": [
        "janmashtami",
        "vaikuntha-ekadashi",
        "tulsi-vivah"
    ],
    "purposes": [
        "devotion",
        "peace",
        "spiritual-growth",
        "protection"
    ],
    "readingTimeMinutes": 4,
    "seoDescription": "Read Shri Hari Stuti in Sanskrit with Hindi meaning. Universal Vishnu-Krishna praise with Gita Charama Shloka and Hare Krishna Mahamantra.",
    "verseCount": 8,
    "source": "Bhagavad Gita / Vishnu Purana / Vaishnava Tradition",
    "createdAt": "2026-03-28T00:00:00Z",
    "updatedAt": "2026-03-28T00:00:00Z",
    "isPublished": true
}